clitogui/__init__.py
clitogui/argument_extractor.py
clitogui/clitogui.py
clitogui/gui.py
clitogui-0.0.1.dist-info/METADATA
clitogui-0.0.1.dist-info/WHEEL
clitogui-0.0.1.dist-info/top_level.txt
clitogui-0.0.1.dist-info/RECORD
